nasti/__init__.py
nasti/cli.py
nasti/exceptions.py
nasti/globals.py
nasti/hooks.py
nasti/mutation.py
nasti/nasti.py
nasti/nastifile.py
nasti/source_handlers.py
nasti/validation.py
tests/__init__.py
tests/mocks.py
tests/test_globals.py
tests/test_hooks.py
tests/test_mutation.py
tests/test_nastifile.py
tests/test_source_handlers.py
tests/test_validation.py
NASTI-0.4.1.dist-info/LICENSE
NASTI-0.4.1.dist-info/METADATA
NASTI-0.4.1.dist-info/WHEEL
NASTI-0.4.1.dist-info/entry_points.txt
NASTI-0.4.1.dist-info/top_level.txt
NASTI-0.4.1.dist-info/RECORD
