Metadata-Version: 2.1
Name: NASTI
Version: 0.4.1
Summary: NASTI's A Strange Templating Implementation
Home-page: https://github.com/adamrdrew/nasti
Author: Adam Drew
Author-email: adamrdrew@live.com
Classifier: Programming Language :: Python :: 3
Classifier: License :: OSI Approved :: GNU General Public License v3 (GPLv3)
Classifier: Operating System :: OS Independent
Requires-Python: >=3.10
License-File: LICENSE
Requires-Dist: click ==8.1.7
Requires-Dist: coverage ==7.3.1
Requires-Dist: iniconfig ==2.0.0
Requires-Dist: jinja2 ==3.1.2
Requires-Dist: markdown-it-py ==3.0.0
Requires-Dist: markupsafe ==2.1.3
Requires-Dist: mdurl ==0.1.2
Requires-Dist: packaging ==23.1
Requires-Dist: pluggy ==1.3.0
Requires-Dist: prompt-toolkit ==3.0.39
Requires-Dist: pygments ==2.16.1
Requires-Dist: pytest ==7.4.2
Requires-Dist: pyyaml ==6.0.1
Requires-Dist: rich ==13.5.3
Requires-Dist: validators ==0.22.0
Requires-Dist: wcwidth ==0.2.6
Provides-Extra: dev
Requires-Dist: appdirs ==1.4.4 ; extra == 'dev'
Requires-Dist: attrs ==23.1.0 ; extra == 'dev'
Requires-Dist: cached-property ==1.5.2 ; extra == 'dev'
Requires-Dist: cerberus ==1.3.5 ; extra == 'dev'
Requires-Dist: certifi ==2023.7.22 ; extra == 'dev'
Requires-Dist: chardet ==5.0.0 ; extra == 'dev'
Requires-Dist: charset-normalizer ==3.2.0 ; extra == 'dev'
Requires-Dist: colorama ==0.4.6 ; extra == 'dev'
Requires-Dist: distlib ==0.3.7 ; extra == 'dev'
Requires-Dist: idna ==3.4 ; extra == 'dev'
Requires-Dist: orderedmultidict ==1.0.1 ; extra == 'dev'
Requires-Dist: packaging ==23.1 ; extra == 'dev'
Requires-Dist: pep517 ==0.13.0 ; extra == 'dev'
Requires-Dist: pip ==23.2.1 ; extra == 'dev'
Requires-Dist: pip-shims ==0.3.4 ; extra == 'dev'
Requires-Dist: pipenv-setup ==3.2.0 ; extra == 'dev'
Requires-Dist: pipfile ==0.0.2 ; extra == 'dev'
Requires-Dist: plette ==0.4.4 ; extra == 'dev'
Requires-Dist: pyparsing ==3.1.1 ; extra == 'dev'
Requires-Dist: python-dateutil ==2.8.2 ; extra == 'dev'
Requires-Dist: requests ==2.31.0 ; extra == 'dev'
Requires-Dist: requirementslib ==1.5.7 ; extra == 'dev'
Requires-Dist: setuptools ==68.2.2 ; extra == 'dev'
Requires-Dist: six ==1.16.0 ; extra == 'dev'
Requires-Dist: toml ==0.10.2 ; extra == 'dev'
Requires-Dist: tomlkit ==0.12.1 ; extra == 'dev'
Requires-Dist: urllib3 ==2.0.5 ; extra == 'dev'
Requires-Dist: vistir ==0.6.1 ; extra == 'dev'
Requires-Dist: wheel ==0.41.2 ; extra == 'dev'
